jetblack_iso8601/__init__.py
jetblack_iso8601/date_time.py
jetblack_iso8601/duration.py
jetblack_iso8601/py.typed
jetblack_iso8601-2.0.0.dist-info/LICENSE
jetblack_iso8601-2.0.0.dist-info/METADATA
jetblack_iso8601-2.0.0.dist-info/WHEEL
jetblack_iso8601-2.0.0.dist-info/top_level.txt
jetblack_iso8601-2.0.0.dist-info/RECORD
