Metadata-Version: 2.1
Name: jetblack-iso8601
Version: 2.0.0
Summary: ISO 8601 support
Author-email: Rob Blackbourn <rob.blackbourn@gmail.com>
License: Apache-2.0
Project-URL: Homepage, https://github.com/rob-blackbourn/jetblack-iso8601
Project-URL: Issues, https://github.com/rob-blackbourn/jetblack-iso8601/issues
Keywords: iso8601,jetblack
Classifier: Programming Language :: Python :: 3
Classifier: License :: OSI Approved :: MIT License
Classifier: Operating System :: OS Independent
Requires-Python: >=3.9
License-File: LICENSE
Provides-Extra: dev
Requires-Dist: pytest ; extra == 'dev'
Requires-Dist: coverage ; extra == 'dev'
Requires-Dist: autopep8 ; extra == 'dev'
Requires-Dist: pylint ; extra == 'dev'
Requires-Dist: mypy ; extra == 'dev'
Provides-Extra: docs
Requires-Dist: mkdocs ; extra == 'docs'
Requires-Dist: mkdocs-material ; extra == 'docs'
Requires-Dist: jetblack-markdown ; extra == 'docs'
Requires-Dist: mike ; extra == 'docs'
